fastGAT/__init__.py
fastGAT/demo.py
fastGAT/fastGAT.py
fastGAT/layer.py
fastGAT/model.py
fastGAT/utils.py
fastGAT/visual.py
fastGAT-0.1.0.dist-info/LICENSE
fastGAT-0.1.0.dist-info/METADATA
fastGAT-0.1.0.dist-info/WHEEL
fastGAT-0.1.0.dist-info/top_level.txt
fastGAT-0.1.0.dist-info/RECORD
