Metadata-Version: 2.1
Name: fastGAT
Version: 0.1.0
Summary: A Fast Graph ATtention networks with ALSH. 
Home-page: UNKNOWN
Author: LiangZi@NEU
Author-email: 2273067585@qq.com
License: UNKNOWN
Platform: UNKNOWN
Classifier: Programming Language :: Python :: 3
Classifier: License :: OSI Approved :: MIT License
Classifier: Operating System :: OS Independent
